{
  "mcpServers": {
    "sqlite-memory": {
      "command": "npx",
      "args": [
        "-y",
        "@modelcontextprotocol/server-sqlite",
        "${HOME}/meteor/data/memory.db"
      ]
    },
    "playwright": {
      "command": "npx",
      "args": ["-y", "@playwright/mcp@latest"],
      "env": { "PLAYWRIGHT_HEADLESS": "1" }
    },
    "fetch": {
      "command": "uvx",
      "args": ["mcp-server-fetch"]
    },
    "github": {
      "command": "npx",
      "args": ["-y", "@github/mcp-server"],
      "env": { "GITHUB_TOKEN": "${GITHUB_TOKEN}" }
    },
    "gmail": {
      "command": "npx",
      "args": ["-y", "@gongrzhe/server-gmail-autoauth-mcp"],
      "env": {
        "GMAIL_OAUTH_CREDENTIALS": "${HOME}/meteor/data/gmail-credentials.json"
      }
    },
    "telegram": {
      "command": "uvx",
      "args": ["tgbot-mcp"],
      "env": {
        "TELEGRAM_BOT_TOKEN": "${TELEGRAM_BOT_TOKEN}",
        "TELEGRAM_CHAT_ID": "${TELEGRAM_CHAT_ID}"
      }
    }
  }
}
